{"id":"coin-7601","title_display":"Coin: 7601","pub_created_display":"Constantine II   (337 to 340), follis, Antioch","access_facet":["Online","In the Library"],"call_number_display":["Coin 7601"],"call_number_browse_s":["Coin 7601"],"location_code_s":["num"],"location":["Special Collections"],"location_display":["Special Collections - Numismatics Collection"],"format":["Coin"],"advanced_location_s":["num"],"notes_display":["Note: symbol on reverse obscured"],"find_place_s":["Antioch, Syria"],"find_date_s":["1934-04-04"],"find_feature_s":["1-1.1m below level of mosaic"],"find_locus_s":["DS 7-O"],"find_number_s":["C2394"],"die_axis_s":["11"],"size_s":["18.5"],"weight_s":["2.396"],"holdings_1display":"{\"numismatics\":{\"location\":\"Special Collections - Numismatics Collection\",\"library\":\"Special Collections\",\"location_code\":\"num\",\"call_number\":\"Coin 7601\",\"call_number_browse\":\"Coin 7601\"}}","numismatic_collection_s":["Antioch"],"numismatic_accession_s":["179: 1939-01-01 Antioch Excavation"],"pub_date_start_sort":330,"pub_date_end_sort":335,"issue_object_type_s":["coin"],"issue_denomination_s":["follis"],"issue_denomination_sort":"follis","issue_metal_s":["Bronze"],"issue_metal_sort":"bronze","issue_ruler_s":["Constantine II   (337 to 340)"],"issue_ruler_sort":"Constantine II   (337 to 340)","issue_master_s":[null],"issue_place_s":["Antioch, Syria, Roman Empire"],"issue_city_s":["Antioch"],"issue_state_s":["Syria"],"issue_region_s":["Roman Empire"],"issue_place_sort":"Antioch, Syria, Roman Empire","issue_obverse_figure_s":["Emperor"],"issue_obverse_part_s":["bust"],"issue_obverse_orientation_s":["facing right"],"issue_obverse_figure_description_s":["laureate, cuirassed"],"issue_obverse_legend_s":["CONSTANTINVSIVNNOBC"],"issue_reverse_figure_s":["Two soldiers"],"issue_reverse_part_s":["standing"],"issue_reverse_orientation_s":["facing each other"],"issue_reverse_figure_description_s":["Two soldiers, helmeted, draped, cuirassed, standing facing each other, each holding reversed spear in outer hand and resting inner hand on shield; between them, two standards"],"issue_reverse_legend_s":["GLOR-IAEXERCITVS | SMANS"],"issue_references_s":["RIC VII Antioch 87"],"issue_references_sort":"RIC VII Antioch 87","issue_monogram_1display":"[]","issue_date_s":["330 to 335"]}