{"bib":[{"mms_id":"99222441306421","record_format":"marc21","linked_record_id":{"value":null,"type":null},"title":"Aliens \u0026 anorexia /","author":"Kraus, Chris,","issn":null,"isbn":"9781584351269 (pbk.)","network_number":["(OCoLC)ocn851826743","7991903","(OCoLC)ocn862844408","(OCoLC)ocn842500102"],"place_of_publication":"Los Angeles, CA :","date_of_publication":"c2013.","publisher_const":"Semiotext(e),","holdings":{"value":null,"link":"https://api-na.hosted.exlibrisgroup.com/almaws/v1/bibs/99222441306421/holdings"},"created_by":"System","created_date":"2020-05-27Z","last_modified_by":"AlmaAdmin","last_modified_date":"2020-08-24Z","suppress_from_publishing":"true","suppress_from_external_search":"false","sync_with_oclc":"NONE","sync_with_libraries_australia":"NONE","originating_system":"OTHER","originating_system_id":"7991903","cataloging_level":{"value":"00","desc":"Default Level"},"anies":["\u003c?xml version=\"1.0\" encoding=\"UTF-16\"?\u003e\u003crecord\u003e\u003cleader\u003e00991cam a2200301 a 4500\u003c/leader\u003e\u003ccontrolfield tag=\"001\"\u003e99222441306421\u003c/controlfield\u003e\u003ccontrolfield tag=\"005\"\u003e20200807122657.0\u003c/controlfield\u003e\u003ccontrolfield tag=\"008\"\u003e131112s2013    mau      b    000 0 eng d\u003c/controlfield\u003e\u003cdatafield ind1=\" \" ind2=\" \" tag=\"019\"\u003e\u003csubfield code=\"a\"\u003e842500102\u003c/subfield\u003e\u003csubfield code=\"a\"\u003e862844408\u003c/subfield\u003e\u003c/datafield\u003e\u003cdatafield ind1=\" \" ind2=\" \" tag=\"020\"\u003e\u003csubfield code=\"a\"\u003e1584351268 (pbk.)\u003c/subfield\u003e\u003c/datafield\u003e\u003cdatafield ind1=\" \" ind2=\" \" tag=\"020\"\u003e\u003csubfield code=\"a\"\u003e9781584351269 (pbk.)\u003c/subfield\u003e\u003c/datafield\u003e\u003cdatafield ind1=\" \" ind2=\" \" tag=\"035\"\u003e\u003csubfield code=\"a\"\u003e7991903\u003c/subfield\u003e\u003c/datafield\u003e\u003cdatafield ind1=\" \" ind2=\" \" tag=\"035\"\u003e\u003csubfield code=\"a\"\u003e(OCoLC)ocn851826743\u003c/subfield\u003e\u003csubfield code=\"z\"\u003e(OCoLC)ocn842500102\u003c/subfield\u003e\u003csubfield code=\"z\"\u003e(OCoLC)ocn862844408\u003c/subfield\u003e\u003c/datafield\u003e\u003cdatafield ind1=\" \" ind2=\" \" tag=\"040\"\u003e\u003csubfield code=\"a\"\u003eCDX\u003c/subfield\u003e\u003csubfield code=\"c\"\u003eCDX\u003c/subfield\u003e\u003csubfield code=\"d\"\u003eNjP\u003c/subfield\u003e\u003c/datafield\u003e\u003cdatafield ind1=\" \" ind2=\"4\" tag=\"050\"\u003e\u003csubfield code=\"a\"\u003ePS3561.R2873\u003c/subfield\u003e\u003csubfield code=\"b\"\u003eA68 2013\u003c/subfield\u003e\u003c/datafield\u003e\u003cdatafield ind1=\" \" ind2=\"4\" tag=\"082\"\u003e\u003csubfield code=\"a\"\u003e813.5\u003c/subfield\u003e\u003csubfield code=\"b\"\u003e23\u003c/subfield\u003e\u003c/datafield\u003e\u003cdatafield ind1=\"1\" ind2=\" \" tag=\"100\"\u003e\u003csubfield code=\"a\"\u003eKraus, Chris,\u003c/subfield\u003e\u003csubfield code=\"e\"\u003eauthor.\u003c/subfield\u003e\u003c/datafield\u003e\u003cdatafield ind1=\"1\" ind2=\"0\" tag=\"245\"\u003e\u003csubfield code=\"a\"\u003eAliens \u0026amp; anorexia /\u003c/subfield\u003e\u003csubfield code=\"c\"\u003eChris Kraus.\u003c/subfield\u003e\u003c/datafield\u003e\u003cdatafield ind1=\"3\" ind2=\" \" tag=\"246\"\u003e\u003csubfield code=\"a\"\u003eAliens and anorexia\u003c/subfield\u003e\u003c/datafield\u003e\u003cdatafield ind1=\" \" ind2=\" \" tag=\"260\"\u003e\u003csubfield code=\"a\"\u003eLos Angeles, CA :\u003c/subfield\u003e\u003csubfield code=\"b\"\u003eSemiotext(e),\u003c/subfield\u003e\u003csubfield code=\"c\"\u003ec2013.\u003c/subfield\u003e\u003c/datafield\u003e\u003cdatafield ind1=\" \" ind2=\" \" tag=\"300\"\u003e\u003csubfield code=\"a\"\u003e261 pages :\u003c/subfield\u003e\u003csubfield code=\"b\"\u003eill. ;\u003c/subfield\u003e\u003csubfield code=\"c\"\u003e23 cm\u003c/subfield\u003e\u003c/datafield\u003e\u003cdatafield ind1=\"1\" ind2=\" \" tag=\"490\"\u003e\u003csubfield code=\"a\"\u003eSemiotext(e) native agents series\u003c/subfield\u003e\u003c/datafield\u003e\u003cdatafield ind1=\" \" ind2=\" \" tag=\"504\"\u003e\u003csubfield code=\"a\"\u003eIncludes bibliographical references.\u003c/subfield\u003e\u003c/datafield\u003e\u003cdatafield ind1=\" \" ind2=\"0\" tag=\"650\"\u003e\u003csubfield code=\"a\"\u003eExperimental fiction.\u003c/subfield\u003e\u003c/datafield\u003e\u003cdatafield ind1=\" \" ind2=\"0\" tag=\"830\"\u003e\u003csubfield code=\"a\"\u003eSemiotext(e) native agents series.\u003c/subfield\u003e\u003c/datafield\u003e\u003cdatafield ind1=\"0\" ind2=\" \" tag=\"852\"\u003e\u003csubfield code=\"0\"\u003e7770428\u003c/subfield\u003e\u003csubfield code=\"b\"\u003ef\u003c/subfield\u003e\u003csubfield code=\"h\"\u003ePS3561.R2873\u003c/subfield\u003e\u003csubfield code=\"i\"\u003eA68 2013\u003c/subfield\u003e\u003c/datafield\u003e\u003cdatafield ind1=\" \" ind2=\" \" tag=\"902\"\u003e\u003csubfield code=\"a\"\u003elm\u003c/subfield\u003e\u003csubfield code=\"b\"\u003em\u003c/subfield\u003e\u003csubfield code=\"6\"\u003ea\u003c/subfield\u003e\u003csubfield code=\"7\"\u003em\u003c/subfield\u003e\u003csubfield code=\"d\"\u003ev\u003c/subfield\u003e\u003csubfield code=\"f\"\u003e1\u003c/subfield\u003e\u003csubfield code=\"e\"\u003e20140320\u003c/subfield\u003e\u003c/datafield\u003e\u003cdatafield ind1=\" \" ind2=\" \" tag=\"904\"\u003e\u003csubfield code=\"a\"\u003ewcs\u003c/subfield\u003e\u003csubfield code=\"b\"\u003eo\u003c/subfield\u003e\u003csubfield code=\"h\"\u003em\u003c/subfield\u003e\u003csubfield code=\"c\"\u003eb\u003c/subfield\u003e\u003csubfield code=\"e\"\u003e20131216\u003c/subfield\u003e\u003c/datafield\u003e\u003cdatafield ind1=\" \" ind2=\" \" tag=\"INT\"\u003e\u003csubfield code=\"a\"\u003eP\u003c/subfield\u003e\u003c/datafield\u003e\u003cdatafield ind1=\" \" ind2=\" \" tag=\"INST\"\u003e\u003csubfield code=\"a\"\u003e01PRI_INST\u003c/subfield\u003e\u003c/datafield\u003e\u003cdatafield ind1=\" \" ind2=\" \" tag=\"AVA\"\u003e\u003csubfield code=\"0\"\u003e99222441306421\u003c/subfield\u003e\u003csubfield code=\"8\"\u003e2281599870006421\u003c/subfield\u003e\u003csubfield code=\"a\"\u003e01PRI_INST\u003c/subfield\u003e\u003csubfield code=\"b\"\u003eMAIN\u003c/subfield\u003e\u003csubfield code=\"c\"\u003eStacks\u003c/subfield\u003e\u003csubfield code=\"d\"\u003ePS3561.R2873 A68 2013\u003c/subfield\u003e\u003csubfield code=\"e\"\u003eavailable\u003c/subfield\u003e\u003csubfield code=\"f\"\u003e1\u003c/subfield\u003e\u003csubfield code=\"g\"\u003e0\u003c/subfield\u003e\u003csubfield code=\"j\"\u003emain\u003c/subfield\u003e\u003csubfield code=\"k\"\u003e0\u003c/subfield\u003e\u003csubfield code=\"p\"\u003e1\u003c/subfield\u003e\u003csubfield code=\"q\"\u003eMain Library\u003c/subfield\u003e\u003c/datafield\u003e\u003c/record\u003e"],"requests":{"value":0,"link":null},"link":null}],"total_record_count":1}
