{
    "Acadians": [
        [
            "Nova Scotia",
            "History",
            "Expulsion, 1755"
        ]
    ],
    "African Americans": [
        [
            "Relations with Indians"
        ],
        [
            "Relations with West Indians"
        ]
    ],
    "Alaska": [
        [
            "Antiquities"
        ]
    ],
    "Alcatraz Island (Calif.)": [
        [
            "History",
            "Indian occupation, 1969-1971"
        ]
    ],
    "American drama": [
        [
            "Indian authors"
        ]
    ],
    "American fiction": [
        [
            "Indian authors"
        ]
    ],
    "American literature": [
        [
            "Eskimo authors"
        ],
        [
            "Indian authors"
        ],
        [
            "Inuit authors"
        ]
    ],
    "American poetry": [
        [
            "Eskimo authors"
        ],
        [
            "Indian authors"
        ]
    ],
    "American prose literature": [
        [
            "Indian authors"
        ]
    ],
    "Argentine poetry": [
        [
            "Indian authors"
        ]
    ],
    "Art": [
        [
            "Indian influences"
        ]
    ],
    "Art, Mexican": [
        [
            "Indian influences"
        ]
    ],
    "Arts, Modern": [
        [
            "Indian influences"
        ]
    ],
    "Autobiography": [
        [
            "Indian authors"
        ]
    ],
    "Bethlehem (Pa.)": [
        [
            "History",
            "Siege, 1755"
        ]
    ],
    "Black people": [
        [
            "Relations with Indians"
        ]
    ],
    "Brazilian literature": [
        [
            "Indian authors"
        ]
    ],
    "Canada": [
        [
            "Civilization",
            "Indian influences"
        ]
    ],
    "Canadian drama": [
        [
            "Indian authors"
        ]
    ],
    "Canadian fiction": [
        [
            "Indian authors"
        ]
    ],
    "Canadian literature": [
        [
            "Indian authors"
        ],
        [
            "Inuit authors"
        ],
        [
            "Me패tis authors"
        ]
    ],
    "Canadian poetry": [
        [
            "Indian authors"
        ]
    ],
    "Canadian prose literature": [
        [
            "Indian authors"
        ]
    ],
    "Catalan language": [
        [
            "Foreign words and phrases",
            "Indian"
        ]
    ],
    "Central American literature": [
        [
            "Indian authors"
        ]
    ],
    "Chiapas (Mexico)": [
        [
            "History",
            "Tzeltal Revolt, 1712"
        ]
    ],
    "Christian art and symbolism": [
        [
            "Mexico",
            "Indian influences"
        ]
    ],
    "Civilization": [
        [
            "Indian influences"
        ]
    ],
    "Classification": [
        [
            "Books",
            "Indian languages"
        ],
        [
            "Books",
            "Indians of North America"
        ]
    ],
    "Colombian literature": [
        [
            "Indian authors"
        ]
    ],
    "Connecticut": [
        [
            "History",
            "French and Indian War, 1754-1763"
        ]
    ],
    "Cooking, Canadian": [
        [
            "Nunavut style"
        ]
    ],
    "Costa Rican literature": [
        [
            "Indian authors"
        ]
    ],
    "Cuba": [
        [
            "Civilization",
            "Indian influences"
        ]
    ],
    "Dominican Republic": [
        [
            "Civilization",
            "Indian influences"
        ]
    ],
    "Ecuador": [
        [
            "Civilization",
            "Indian influences"
        ]
    ],
    "Embroidery": [
        [
            "Arctic regions"
        ]
    ],
    "English language": [
        [
            "Foreign words and phrases",
            "Algonquian"
        ],
        [
            "Foreign words and phrases",
            "Indian"
        ],
        [
            "Study and teaching (Elementary)",
            "Indian speakers"
        ],
        [
            "Study and teaching (Elementary)",
            "Inuit speakers"
        ],
        [
            "Study and teaching (Primary)",
            "Eskimo speakers"
        ],
        [
            "Study and teaching (Primary)",
            "Inuit speakers"
        ],
        [
            "Study and teaching",
            "Eskimo speakers"
        ],
        [
            "Study and teaching",
            "Inuit speakers"
        ]
    ],
    "English literature": [
        [
            "Indian influences"
        ],
        [
            "Maya authors"
        ],
        [
            "Mayan influences"
        ]
    ],
    "Ethnology": [
        [
            "Central America"
        ],
        [
            "Mexico"
        ],
        [
            "North America"
        ],
        [
            "South America"
        ]
    ],
    "Europe": [
        [
            "Civilization",
            "Indian influences"
        ]
    ],
    "Feminism": [
        [
            "Indian influences"
        ]
    ],
    "Fort Frontenac (Ont. : Fort)": [
        [
            "Capture, 1758"
        ]
    ],
    "Fort Oswego (Oswego, N.Y.)": [
        [
            "Capture, 1756"
        ]
    ],
    "Fort William Henry (N.Y.)": [
        [
            "Capture, 1757"
        ]
    ],
    "France": [
        [
            "Civilization",
            "Indian influences"
        ]
    ],
    "French language": [
        [
            "Foreign words and phrases",
            "Indian"
        ]
    ],
    "French-Canadian fiction": [
        [
            "Indian authors"
        ]
    ],
    "French-Canadian poetry": [
        [
            "Indian authors"
        ]
    ],
    "German language": [
        [
            "Foreign words and phrases",
            "Indian"
        ]
    ],
    "Guatemalan poetry": [
        [
            "Indian authors"
        ]
    ],
    "Hawaiian language": [
        [
            "Influence on Eskimo"
        ]
    ],
    "Healing": [
        [
            "Religious aspects",
            "Indian Shaker Church"
        ]
    ],
    "Honduran poetry": [
        [
            "Indian authors"
        ]
    ],
    "Information storage and retrieval systems": [
        [
            "Indians of North America"
        ]
    ],
    "Jesus Christ": [
        [
            "Indian interpretations"
        ]
    ],
    "Latin America": [
        [
            "Civilization",
            "Indian influences"
        ]
    ],
    "Latin American literature": [
        [
            "Indian authors"
        ]
    ],
    "Libraries": [
        [
            "Special collections",
            "Eskimo languages"
        ],
        [
            "Special collections",
            "Indians"
        ],
        [
            "Special collections",
            "Indians of North America"
        ]
    ],
    "Literature": [
        [
            "Indian authors"
        ]
    ],
    "Louisbourg (N.S.)": [
        [
            "History",
            "Siege, 1758"
        ]
    ],
    "Maryland": [
        [
            "History",
            "French and Indian War, 1754-1763"
        ]
    ],
    "Massachusetts": [
        [
            "History",
            "French and Indian War, 1754-1763"
        ],
        [
            "Politics and government",
            "1755-1763"
        ]
    ],
    "Mexican literature": [
        [
            "Indian authors"
        ]
    ],
    "Mexican poetry": [
        [
            "Indian authors"
        ]
    ],
    "Mexico": [
        [
            "Civilization",
            "Indian influences"
        ]
    ],
    "Music": [
        [
            "Indian influences"
        ]
    ],
    "Names, Geographical": [
        [
            "Eskimo"
        ],
        [
            "Inuit"
        ],
        [
            "Mayan"
        ]
    ],
    "Names, Personal": [
        [
            "Indian"
        ],
        [
            "Maya"
        ]
    ],
    "New England": [
        [
            "History",
            "French and Indian War, 1754-1763"
        ]
    ],
    "New York (State)": [
        [
            "History",
            "French and Indian War, 1754-1763"
        ]
    ],
    "North America": [
        [
            "Civilization",
            "Indian influences"
        ]
    ],
    "North Carolina": [
        [
            "History",
            "French and Indian War, 1754-1763"
        ]
    ],
    "Nunavut": [
        [
            "Antiquities"
        ]
    ],
    "Old Fort Niagara (N.Y.)": [
        [
            "Siege, 1759"
        ]
    ],
    "Ontario": [
        [
            "History",
            "French and Indian War, 1754-1763"
        ]
    ],
    "Paraguay": [
        [
            "Civilization",
            "Indian influences"
        ]
    ],
    "Pennsylvania": [
        [
            "History",
            "French and Indian War, 1754-1763"
        ]
    ],
    "Peru": [
        [
            "Civilization",
            "Indian influences"
        ],
        [
            "History",
            "Insurrection of Tupac Amaru, 1780-1781"
        ],
        [
            "History",
            "To 1548"
        ]
    ],
    "Peruvian literature": [
        [
            "Indian authors"
        ]
    ],
    "Peruvian poetry": [
        [
            "Indian authors"
        ]
    ],
    "Pittsburgh (Pa.)": [
        [
            "History",
            "French and Indian War, 1754-1763"
        ]
    ],
    "Puerto Rico": [
        [
            "History",
            "Indian Rebellion, 1511"
        ]
    ],
    "Que패bec (Province)": [
        [
            "History",
            "Native Crisis, 1990"
        ]
    ],
    "Que패bec (Que패bec)": [
        [
            "History",
            "French and Indian War, 1754-1763"
        ]
    ],
    "Rhode Island": [
        [
            "History",
            "French and Indian War, 1754-1763"
        ]
    ],
    "Royalton (Vt.)": [
        [
            "History",
            "Burning by the British and Indians, 1780"
        ]
    ],
    "Russia (Federation)": [
        [
            "Civilization",
            "Indian influences"
        ]
    ],
    "Russian language": [
        [
            "Influence on Eskimo"
        ]
    ],
    "Saint Vincent": [
        [
            "History",
            "Carib War, 1795-1796"
        ]
    ],
    "Spanish language": [
        [
            "Foreign elements",
            "Maya"
        ],
        [
            "Foreign elements",
            "Mayan"
        ],
        [
            "Foreign words and phrases",
            "Indian"
        ],
        [
            "Foreign words and phrases",
            "Maya"
        ],
        [
            "Influence on Maya"
        ],
        [
            "Influence on Mayan"
        ],
        [
            "Study and teaching (Elementary)",
            "Mayan speakers"
        ],
        [
            "Study and teaching",
            "Maya speakers"
        ],
        [
            "Study and teaching",
            "Mayan speakers"
        ]
    ],
    "Speeches, addresses, etc., American": [
        [
            "Indian authors"
        ]
    ],
    "Subject headings": [
        [
            "Eskimos"
        ],
        [
            "Indians"
        ],
        [
            "Indians of North America"
        ]
    ],
    "Ticonderoga (N.Y.)": [
        [
            "History",
            "French and Indian War, 1754-1763"
        ]
    ],
    "Trading posts": [
        [
            "Alberta"
        ],
        [
            "Arizona"
        ],
        [
            "Central America"
        ],
        [
            "North America"
        ],
        [
            "North Dakota"
        ],
        [
            "South Dakota"
        ],
        [
            "Washington (State)"
        ]
    ],
    "Trinidad and Tobago": [
        [
            "Civilization",
            "Indian influences"
        ]
    ],
    "United States": [
        [
            "Antiquities"
        ],
        [
            "Armed Forces",
            "Indians"
        ],
        [
            "Civilization",
            "Indian influences"
        ],
        [
            "History",
            "Civil War, 1861-1865",
            "Participation, Indian"
        ],
        [
            "History",
            "French and Indian War, 1754-1763"
        ],
        [
            "History",
            "King George's War, 1744-1748"
        ],
        [
            "History",
            "King William's War, 1689-1697"
        ],
        [
            "History",
            "Queen Anne's War, 1702-1713"
        ],
        [
            "Politics and government",
            "1754-1763"
        ]
    ],
    "United States.": [
        [
            "Army",
            "Indian troops"
        ],
        [
            "Navy",
            "Indians"
        ]
    ],
    "Uruguay": [
        [
            "Civilization",
            "Indian influences"
        ]
    ],
    "Venezuela": [
        [
            "Civilization",
            "Indian influences"
        ]
    ],
    "Venezuelan literature": [
        [
            "Indian authors"
        ]
    ],
    "Virginia": [
        [
            "History",
            "French and Indian War, 1754-1763"
        ]
    ],
    "White people": [
        [
            "Relations with Indians"
        ]
    ],
    "Women artists": [
        [
            "Arctic regions"
        ]
    ],
    "World War, 1939-1945": [
        [
            "Indians"
        ],
        [
            "Participation, Indian"
        ]
    ],
    "Wounded Knee (S.D.)": [
        [
            "History",
            "Indian occupation, 1973"
        ]
    ]
}